{
  "manifestVersion": "3.2",
  "admin": {
    "address": "0xa01aC3F68586f610DDa4A4BB5ad73C7856f1Bc86",
    "txHash": "0xdbcce4ce70ccbbcee3fb2fbc0697e8b8cf865c00dbcf9ad6889cd36a26cd46a1"
  },
  "proxies": [
    {
      "address": "0x5F68543e0d6694CdfBd6593844cDE01577Ada3CA",
      "txHash": "0x3749dd53b3142bf825fd0fa7af99779f917b139bb52e544e1e12f2f0f5159972",
      "kind": "transparent"
    },
    {
      "address": "0x4425b36e408fc96d5Ed1Ad3dc930Eb8708A8a055",
      "txHash": "0x6dbe8de0be79d8edafb3187acd1fa7dae7d5bd623a9851fbdacb679b23c235d3",
      "kind": "transparent"
    },
    {
      "address": "0x8D9e45E33b5dd3E6ce41531C75c6351AF14FA7E4",
      "txHash": "0xe0418ee85c0310004ae1d23166101eb1237b644fc6703f22e40ba867e9a7183c",
      "kind": "transparent"
    },
    {
      "address": "0x69637181743172aE1FDD2F0b31781C5d1EcC83a7",
      "txHash": "0x15cefcba0bf6695de569eba9680980c3eabb41bb4c4dd41a784a7fe27cf0cb83",
      "kind": "transparent"
    }
  ],
  "impls": {
    "cdb65339435acc2e41d3aa8ffe0a4bb89e30d8ee5673066f7ae647c057b8e62f": {
      "address": "0xA265727EE475D735b80B18f5ECB117e79Eb45fD4",
      "txHash": "0xea1b06acb45aafbc7edfcda2a966cf225127575b9a4337ff72b3a39dd8c59008",
      "layout": {
        "storage": [
          {
            "label": "_initialized",
            "offset": 0,
            "slot": "0",
            "type": "t_bool",
            "contract": "Initializable",
            "src": "@openzeppelin/contracts-upgradeable/proxy/utils/Initializable.sol:39"
          },
          {
            "label": "_initializing",
            "offset": 1,
            "slot": "0",
            "type": "t_bool",
            "contract": "Initializable",
            "src": "@openzeppelin/contracts-upgradeable/proxy/utils/Initializable.sol:44"
          },
          {
            "label": "__gap",
            "offset": 0,
            "slot": "1",
            "type": "t_array(t_uint256)50_storage",
            "contract": "ERC165Upgradeable",
            "src": "@openzeppelin/contracts-upgradeable/utils/introspection/ERC165Upgradeable.sol:41"
          },
          {
            "label": "__gap",
            "offset": 0,
            "slot": "51",
            "type": "t_array(t_uint256)50_storage",
            "contract": "ERC1155ReceiverUpgradeable",
            "src": "@openzeppelin/contracts-upgradeable/token/ERC1155/utils/ERC1155ReceiverUpgradeable.sol:31"
          },
          {
            "label": "__gap",
            "offset": 0,
            "slot": "101",
            "type": "t_array(t_uint256)50_storage",
            "contract": "ERC1155HolderUpgradeable",
            "src": "@openzeppelin/contracts-upgradeable/token/ERC1155/utils/ERC1155HolderUpgradeable.sol:48"
          },
          {
            "label": "__gap",
            "offset": 0,
            "slot": "151",
            "type": "t_array(t_uint256)50_storage",
            "contract": "ContextUpgradeable",
            "src": "@openzeppelin/contracts-upgradeable/utils/ContextUpgradeable.sol:36"
          },
          {
            "label": "_owner",
            "offset": 0,
            "slot": "201",
            "type": "t_address",
            "contract": "OwnableUpgradeable",
            "src": "@openzeppelin/contracts-upgradeable/access/OwnableUpgradeable.sol:22"
          },
          {
            "label": "__gap",
            "offset": 0,
            "slot": "202",
            "type": "t_array(t_uint256)49_storage",
            "contract": "OwnableUpgradeable",
            "src": "@openzeppelin/contracts-upgradeable/access/OwnableUpgradeable.sol:87"
          },
          {
            "label": "trades",
            "offset": 0,
            "slot": "251",
            "type": "t_mapping(t_uint256,t_struct(Trade)863_storage)",
            "contract": "CruzoMarket",
            "src": "contracts/marketplace/CruzoMarket.sol:22"
          },
          {
            "label": "tradeCounter",
            "offset": 0,
            "slot": "252",
            "type": "t_uint256",
            "contract": "CruzoMarket",
            "src": "contracts/marketplace/CruzoMarket.sol:24"
          }
        ],
        "types": {
          "t_address": {
            "label": "address",
            "numberOfBytes": "20"
          },
          "t_address_payable": {
            "label": "address payable",
            "numberOfBytes": "20"
          },
          "t_array(t_uint256)49_storage": {
            "label": "uint256[49]",
            "numberOfBytes": "1568"
          },
          "t_array(t_uint256)50_storage": {
            "label": "uint256[50]",
            "numberOfBytes": "1600"
          },
          "t_bool": {
            "label": "bool",
            "numberOfBytes": "1"
          },
          "t_bytes32": {
            "label": "bytes32",
            "numberOfBytes": "32"
          },
          "t_mapping(t_uint256,t_struct(Trade)863_storage)": {
            "label": "mapping(uint256 => struct CruzoMarket.Trade)",
            "numberOfBytes": "32"
          },
          "t_struct(Trade)863_storage": {
            "label": "struct CruzoMarket.Trade",
            "members": [
              {
                "label": "poster",
                "type": "t_address_payable",
                "offset": 0,
                "slot": "0"
              },
              {
                "label": "tokenAddress",
                "type": "t_address",
                "offset": 0,
                "slot": "1"
              },
              {
                "label": "itemId",
                "type": "t_uint256",
                "offset": 0,
                "slot": "2"
              },
              {
                "label": "amount",
                "type": "t_uint256",
                "offset": 0,
                "slot": "3"
              },
              {
                "label": "price",
                "type": "t_uint256",
                "offset": 0,
                "slot": "4"
              },
              {
                "label": "status",
                "type": "t_bytes32",
                "offset": 0,
                "slot": "5"
              }
            ],
            "numberOfBytes": "192"
          },
          "t_uint256": {
            "label": "uint256",
            "numberOfBytes": "32"
          }
        }
      }
    },
    "f8f83560b65b7dac57fddcee74d0bb860d1d83ef4543f45ba9622e026559664a": {
      "address": "0xD114DC21A2bf82f26a13b287BAe59C74f1477d5b",
      "txHash": "0x93f55a4bcf98390557917d2245cc89470dad7697c5b5d8d4e74c710d8df1e8ad",
      "layout": {
        "storage": [
          {
            "label": "_initialized",
            "offset": 0,
            "slot": "0",
            "type": "t_bool",
            "contract": "Initializable",
            "src": "@openzeppelin/contracts-upgradeable/proxy/utils/Initializable.sol:39"
          },
          {
            "label": "_initializing",
            "offset": 1,
            "slot": "0",
            "type": "t_bool",
            "contract": "Initializable",
            "src": "@openzeppelin/contracts-upgradeable/proxy/utils/Initializable.sol:44"
          },
          {
            "label": "__gap",
            "offset": 0,
            "slot": "1",
            "type": "t_array(t_uint256)50_storage",
            "contract": "ContextUpgradeable",
            "src": "@openzeppelin/contracts-upgradeable/utils/ContextUpgradeable.sol:36"
          },
          {
            "label": "__gap",
            "offset": 0,
            "slot": "51",
            "type": "t_array(t_uint256)50_storage",
            "contract": "ERC165Upgradeable",
            "src": "@openzeppelin/contracts-upgradeable/utils/introspection/ERC165Upgradeable.sol:41"
          },
          {
            "label": "_balances",
            "offset": 0,
            "slot": "101",
            "type": "t_mapping(t_uint256,t_mapping(t_address,t_uint256))",
            "contract": "ERC1155Upgradeable",
            "src": "@openzeppelin/contracts-upgradeable/token/ERC1155/ERC1155Upgradeable.sol:25"
          },
          {
            "label": "_operatorApprovals",
            "offset": 0,
            "slot": "102",
            "type": "t_mapping(t_address,t_mapping(t_address,t_bool))",
            "contract": "ERC1155Upgradeable",
            "src": "@openzeppelin/contracts-upgradeable/token/ERC1155/ERC1155Upgradeable.sol:28"
          },
          {
            "label": "_uri",
            "offset": 0,
            "slot": "103",
            "type": "t_string_storage",
            "contract": "ERC1155Upgradeable",
            "src": "@openzeppelin/contracts-upgradeable/token/ERC1155/ERC1155Upgradeable.sol:31"
          },
          {
            "label": "__gap",
            "offset": 0,
            "slot": "104",
            "type": "t_array(t_uint256)47_storage",
            "contract": "ERC1155Upgradeable",
            "src": "@openzeppelin/contracts-upgradeable/token/ERC1155/ERC1155Upgradeable.sol:475"
          },
          {
            "label": "_totalSupply",
            "offset": 0,
            "slot": "151",
            "type": "t_mapping(t_uint256,t_uint256)",
            "contract": "ERC1155SupplyUpgradeable",
            "src": "@openzeppelin/contracts-upgradeable/token/ERC1155/extensions/ERC1155SupplyUpgradeable.sol:23"
          },
          {
            "label": "__gap",
            "offset": 0,
            "slot": "152",
            "type": "t_array(t_uint256)49_storage",
            "contract": "ERC1155SupplyUpgradeable",
            "src": "@openzeppelin/contracts-upgradeable/token/ERC1155/extensions/ERC1155SupplyUpgradeable.sol:70"
          },
          {
            "label": "_owner",
            "offset": 0,
            "slot": "201",
            "type": "t_address",
            "contract": "OwnableUpgradeable",
            "src": "@openzeppelin/contracts-upgradeable/access/OwnableUpgradeable.sol:22"
          },
          {
            "label": "__gap",
            "offset": 0,
            "slot": "202",
            "type": "t_array(t_uint256)49_storage",
            "contract": "OwnableUpgradeable",
            "src": "@openzeppelin/contracts-upgradeable/access/OwnableUpgradeable.sol:87"
          },
          {
            "label": "_paused",
            "offset": 0,
            "slot": "251",
            "type": "t_bool",
            "contract": "PausableUpgradeable",
            "src": "@openzeppelin/contracts-upgradeable/security/PausableUpgradeable.sol:29"
          },
          {
            "label": "__gap",
            "offset": 0,
            "slot": "252",
            "type": "t_array(t_uint256)49_storage",
            "contract": "PausableUpgradeable",
            "src": "@openzeppelin/contracts-upgradeable/security/PausableUpgradeable.sol:102"
          },
          {
            "label": "creators",
            "offset": 0,
            "slot": "301",
            "type": "t_mapping(t_uint256,t_address)",
            "contract": "ERC1155CruzoBase",
            "src": "contracts/tokens/ERC1155CruzoBase.sol:19"
          },
          {
            "label": "_uriType",
            "offset": 0,
            "slot": "302",
            "type": "t_enum(URIType)2848",
            "contract": "ERC1155URI",
            "src": "contracts/tokens/ERC1155URI.sol:18"
          },
          {
            "label": "_tokenURIs",
            "offset": 0,
            "slot": "303",
            "type": "t_mapping(t_uint256,t_string_storage)",
            "contract": "ERC1155URI",
            "src": "contracts/tokens/ERC1155URI.sol:21"
          },
          {
            "label": "_baseURI",
            "offset": 0,
            "slot": "304",
            "type": "t_string_storage",
            "contract": "ERC1155URI",
            "src": "contracts/tokens/ERC1155URI.sol:24"
          },
          {
            "label": "__gap",
            "offset": 0,
            "slot": "305",
            "type": "t_array(t_uint256)50_storage",
            "contract": "ERC1155URI",
            "src": "contracts/tokens/ERC1155URI.sol:133"
          },
          {
            "label": "_tokenIds",
            "offset": 0,
            "slot": "355",
            "type": "t_struct(Counter)2048_storage",
            "contract": "Cruzo1155",
            "src": "contracts/tokens/Cruzo1155.sol:9"
          },
          {
            "label": "marketAddress",
            "offset": 0,
            "slot": "356",
            "type": "t_address",
            "contract": "Cruzo1155",
            "src": "contracts/tokens/Cruzo1155.sol:10"
          },
          {
            "label": "name",
            "offset": 0,
            "slot": "357",
            "type": "t_string_storage",
            "contract": "Cruzo1155",
            "src": "contracts/tokens/Cruzo1155.sol:12"
          },
          {
            "label": "symbol",
            "offset": 0,
            "slot": "358",
            "type": "t_string_storage",
            "contract": "Cruzo1155",
            "src": "contracts/tokens/Cruzo1155.sol:13"
          }
        ],
        "types": {
          "t_address": {
            "label": "address",
            "numberOfBytes": "20"
          },
          "t_array(t_uint256)47_storage": {
            "label": "uint256[47]",
            "numberOfBytes": "1504"
          },
          "t_array(t_uint256)49_storage": {
            "label": "uint256[49]",
            "numberOfBytes": "1568"
          },
          "t_array(t_uint256)50_storage": {
            "label": "uint256[50]",
            "numberOfBytes": "1600"
          },
          "t_bool": {
            "label": "bool",
            "numberOfBytes": "1"
          },
          "t_enum(URIType)2848": {
            "label": "enum ERC1155URI.URIType",
            "members": [
              "DEFAULT",
              "IPFS",
              "ID",
              "URI"
            ],
            "numberOfBytes": "1"
          },
          "t_mapping(t_address,t_bool)": {
            "label": "mapping(address => bool)",
            "numberOfBytes": "32"
          },
          "t_mapping(t_address,t_mapping(t_address,t_bool))": {
            "label": "mapping(address => mapping(address => bool))",
            "numberOfBytes": "32"
          },
          "t_mapping(t_address,t_uint256)": {
            "label": "mapping(address => uint256)",
            "numberOfBytes": "32"
          },
          "t_mapping(t_uint256,t_address)": {
            "label": "mapping(uint256 => address)",
            "numberOfBytes": "32"
          },
          "t_mapping(t_uint256,t_mapping(t_address,t_uint256))": {
            "label": "mapping(uint256 => mapping(address => uint256))",
            "numberOfBytes": "32"
          },
          "t_mapping(t_uint256,t_string_storage)": {
            "label": "mapping(uint256 => string)",
            "numberOfBytes": "32"
          },
          "t_mapping(t_uint256,t_uint256)": {
            "label": "mapping(uint256 => uint256)",
            "numberOfBytes": "32"
          },
          "t_string_storage": {
            "label": "string",
            "numberOfBytes": "32"
          },
          "t_struct(Counter)2048_storage": {
            "label": "struct CountersUpgradeable.Counter",
            "members": [
              {
                "label": "_value",
                "type": "t_uint256",
                "offset": 0,
                "slot": "0"
              }
            ],
            "numberOfBytes": "32"
          },
          "t_uint256": {
            "label": "uint256",
            "numberOfBytes": "32"
          }
        }
      }
    }
  }
}
